.gitignore
LICENSE
README.md
setup.py
.github/workflows/pypi_publish.yaml
adam_atan2/__init__.py
adam_atan2/adam_atan2.py
adam_atan2/adam_atan2_test.py
adam_atan2.egg-info/PKG-INFO
adam_atan2.egg-info/SOURCES.txt
adam_atan2.egg-info/dependency_links.txt
adam_atan2.egg-info/top_level.txt
csrc/adam_atan2.cu
csrc/adam_atan2.h
csrc/ops.cu