Metadata-Version: 2.4
Name: adam_atan2
Version: 0.0.3
Summary: Adam-atan2 Fused Optimizer
Home-page: https://github.com/imoneoi/adam_atan2
Author: One
Author-email: imonenext@gmail.com
Classifier: Programming Language :: Python :: 3
Classifier: License :: OSI Approved :: Apache Software License
Classifier: Operating System :: Unix
License-File: LICENSE
Dynamic: author
Dynamic: author-email
Dynamic: classifier
Dynamic: description
Dynamic: description-content-type
Dynamic: home-page
Dynamic: license-file
Dynamic: summary
